six.py
six_sesdxcv2-1.17.0.dist-info/METADATA
six_sesdxcv2-1.17.0.dist-info/WHEEL
six_sesdxcv2-1.17.0.dist-info/top_level.txt
six_sesdxcv2-1.17.0.dist-info/RECORD
