Metadata-Version: 2.1
Name: six-sesdxcv2
Version: 1.17.0
Summary: Python 2 and 3 compatibility utilities
Home-page: https://github.com/benjaminp/six
Author: Rachit Mishra
Author-email: abc@dxc.com
License: MIT
Classifier: Development Status :: 5 - Production/Stable
Classifier: Programming Language :: Python :: 2
Classifier: Programming Language :: Python :: 3
Classifier: Intended Audience :: Developers
Classifier: License :: OSI Approved :: MIT License
Classifier: Topic :: Software Development :: Libraries
Classifier: Topic :: Utilities
Requires-Python: >=2.7, !=3.0.*, !=3.1.*, !=3.2.*
